pytest_paramark.py
pytest_paramark-0.1.1.dist-info/LICENSE
pytest_paramark-0.1.1.dist-info/METADATA
pytest_paramark-0.1.1.dist-info/WHEEL
pytest_paramark-0.1.1.dist-info/entry_points.txt
pytest_paramark-0.1.1.dist-info/top_level.txt
pytest_paramark-0.1.1.dist-info/RECORD
