Metadata-Version: 2.1
Name: pytest-paramark
Version: 0.1.1
Summary: Configure pytest fixtures using a combination of"parametrize" and markers
Home-page: https://github.com/mrzechonek/pytest-paramark
Author: Michał Lowas-Rzechonek
Author-email: michal@rzechonek.net
Maintainer: Michał Lowas-Rzechonek
Maintainer-email: michal@rzechonek.net
License: MIT
Platform: UNKNOWN
Classifier: Development Status :: 4 - Beta
Classifier: Framework :: Pytest
Classifier: Intended Audience :: Developers
Classifier: Topic :: Software Development :: Testing
Classifier: Programming Language :: Python
Classifier: Programming Language :: Python :: 3
Classifier: Programming Language :: Python :: 3.4
Classifier: Programming Language :: Python :: 3.5
Classifier: Programming Language :: Python :: 3.6
Classifier: Programming Language :: Python :: 3.7
Classifier: Programming Language :: Python :: Implementation :: CPython
Classifier: Programming Language :: Python :: Implementation :: PyPy
Classifier: Operating System :: OS Independent
Classifier: License :: OSI Approved :: MIT License
Requires-Python: >=3.4
Requires-Dist: pytest (>=4.5.0)
